pyddd/__init__.py
pyddd/application/__init__.py
pyddd/application/abstractions.py
pyddd/application/application.py
pyddd/application/condition.py
pyddd/application/exceptions.py
pyddd/application/executor.py
pyddd/application/handler.py
pyddd/application/module.py
pyddd/application/signal_manager.py
pyddd/application/retry/__init__.py
pyddd/application/retry/backoff.py
pyddd/application/retry/none.py
pyddd/application/retry/tc_retry.py
pyddd/domain/__init__.py
pyddd/domain/abstractions.py
pyddd/domain/command.py
pyddd/domain/entity.py
pyddd/domain/event.py
pyddd/domain/event_sourcing.py
pyddd/domain/message.py
pyddd/domain/types.py
pyddd/infrastructure/__init__.py
pyddd/infrastructure/persistence/__init__.py
pyddd/infrastructure/persistence/abstractions.py
pyddd/infrastructure/persistence/uow.py
pyddd/infrastructure/persistence/event_store/__init__.py
pyddd/infrastructure/persistence/event_store/exceptions.py
pyddd/infrastructure/persistence/event_store/in_memory.py
pyddd/infrastructure/persistence/event_store/postgres.py
pyddd/infrastructure/transport/__init__.py
pyddd/infrastructure/transport/asyncio/__init__.py
pyddd/infrastructure/transport/asyncio/domain/__init__.py
pyddd/infrastructure/transport/asyncio/domain/abstractions.py
pyddd/infrastructure/transport/asyncio/domain/ask_policy.py
pyddd/infrastructure/transport/asyncio/domain/consumer.py
pyddd/infrastructure/transport/asyncio/domain/notification.py
pyddd/infrastructure/transport/asyncio/domain/queue.py
pyddd/infrastructure/transport/asyncio/redis/__init__.py
pyddd/infrastructure/transport/asyncio/redis/pubsub/__init__.py
pyddd/infrastructure/transport/asyncio/redis/pubsub/consumer.py
pyddd/infrastructure/transport/asyncio/redis/pubsub/publisher.py
pyddd/infrastructure/transport/asyncio/redis/stream_group/__init__.py
pyddd/infrastructure/transport/asyncio/redis/stream_group/consumer.py
pyddd/infrastructure/transport/asyncio/redis/stream_group/publisher.py
pyddd/infrastructure/transport/core/__init__.py
pyddd-0.22.0.dist-info/METADATA
pyddd-0.22.0.dist-info/WHEEL
pyddd-0.22.0.dist-info/licenses/LICENSE
pyddd-0.22.0.dist-info/RECORD
