Metadata-Version: 2.4
Name: pyddd
Version: 0.22.0
Summary: Domain-Driven Design for Python
Project-URL: Homepage, https://github.com/vmorugin/pyddd
Project-URL: Issues, https://github.com/vmorugin/pyddd/issues
License-Expression: MIT
License-File: LICENSE
Keywords: cqrs,cqs,ddd,ddd python,domain driven design,domain-driven design,event driven
Classifier: License :: OSI Approved :: MIT License
Classifier: Programming Language :: Python
Classifier: Programming Language :: Python :: 3.10
Classifier: Programming Language :: Python :: 3.11
Classifier: Programming Language :: Python :: 3.12
Classifier: Topic :: Software Development :: Libraries
Requires-Python: >=3.10
Requires-Dist: pydantic<3.0.0,>=1.10.4
Provides-Extra: backoff-retry
Requires-Dist: backoff>=2.0.0; extra == 'backoff-retry'
Provides-Extra: tenacity-retry
Requires-Dist: tenacity>=9.0.0; extra == 'tenacity-retry'
Provides-Extra: transport-redis
Requires-Dist: redis>=3.5.0; extra == 'transport-redis'
